odoo/addons/crm_exception/README.rst
odoo/addons/crm_exception/__init__.py
odoo/addons/crm_exception/__manifest__.py
odoo/addons/crm_exception/demo/crm_exception_demo.xml
odoo/addons/crm_exception/i18n/crm_exception.pot
odoo/addons/crm_exception/i18n/it.po
odoo/addons/crm_exception/models/__init__.py
odoo/addons/crm_exception/models/crm_lead.py
odoo/addons/crm_exception/models/exception_rule.py
odoo/addons/crm_exception/readme/CONFIGURE.md
odoo/addons/crm_exception/readme/CONTRIBUTORS.md
odoo/addons/crm_exception/readme/DESCRIPTION.md
odoo/addons/crm_exception/readme/ROADMAP.md
odoo/addons/crm_exception/static/description/icon.png
odoo/addons/crm_exception/static/description/index.html
odoo/addons/crm_exception/tests/__init__.py
odoo/addons/crm_exception/tests/test_crm_exception.py
odoo/addons/crm_exception/views/base_exception_views.xml
odoo/addons/crm_exception/views/crm_lead_views.xml
odoo_addon_crm_exception-17.0.1.0.0.2.dist-info/METADATA
odoo_addon_crm_exception-17.0.1.0.0.2.dist-info/WHEEL
odoo_addon_crm_exception-17.0.1.0.0.2.dist-info/top_level.txt
odoo_addon_crm_exception-17.0.1.0.0.2.dist-info/RECORD
