Metadata-Version: 2.1
Name: odoo-addon-crm_exception
Version: 17.0.1.0.0.2
Requires-Python: >=3.10
Requires-Dist: odoo-addon-base_exception>=17.0dev,<17.1dev
Requires-Dist: odoo>=17.0a,<17.1dev
Summary: CRM Exception
Home-page: https://github.com/OCA/crm
License: AGPL-3
Author: Quartile Limited, Odoo Community Association (OCA)
Author-email: support@odoo-community.org
Classifier: Programming Language :: Python
Classifier: Framework :: Odoo
Classifier: Framework :: Odoo :: 17.0
Classifier: License :: OSI Approved :: GNU Affero General Public License v3
